{
  "B_Fat": "0",
  "B_Inj": "0",
  "B_KSI": "0",
  "B_Sev": "0",
  "MV_KSI": "0",
  "M_Fat": "0",
  "M_Inj": "0",
  "M_Sev": "0",
  "NodeID_1": "0049782",
  "P_Fat": "0",
  "P_HCC_CLASS": "Middle Third",
  "P_HCC_STREETNAME": "Wetherole Street",
  "P_Inj": "0",
  "P_KSI": "0",
  "P_Sev": "0",
  "hcc_text": "Wetherole Street is a pedestrian high crash corridor (middle third for pedestrian deaths and serious injuries per mile in Queens)",
  "info": "",
  "intersection": "Wetherole Street and 62nd Avenue"
}