{
  "P_HCC_CLASS": "Top 10%",
  "P_KSI": "0",
  "B_Sev": "0",
  "P_Inj": "0",
  "info": "There were 3 injuries caused by traffic crashes here between 2009 and 2012.",
  "B_Inj": "0",
  "P_Fat": "0",
  "P_Sev": "0",
  "M_Inj": "3",
  "M_Sev": "0",
  "NodeID_1": "0037261",
  "M_Fat": "0",
  "P_HCC_STREETNAME": "Guy R Brewer Boulevard",
  "hcc_text": "Guy R Brewer Boulevard is a pedestrian high crash corridor (top 10% for pedestrian deaths and serious injuries per mile in Queens)",
  "MV_KSI": "0",
  "intersection": "Guy R Brewer Boulevard and Mathias Avenue",
  "B_Fat": "0",
  "B_KSI": "0"
}