{
  "B_Fat": "0",
  "B_Inj": "0",
  "B_KSI": "0",
  "B_Sev": "0",
  "MV_KSI": "1",
  "M_Fat": "0",
  "M_Inj": "3",
  "M_Sev": "1",
  "NodeID_1": "0041105",
  "P_Fat": "0",
  "P_HCC_CLASS": "Middle Third",
  "P_HCC_STREETNAME": "56th Road",
  "P_Inj": "0",
  "P_KSI": "0",
  "P_Sev": "0",
  "hcc_text": "56th Road is a pedestrian high crash corridor (middle third for pedestrian deaths and serious injuries per mile in Queens)",
  "info": "There was 1 severe injury caused by traffic crashes here between 2009 and 2012.",
  "intersection": "56th Road at 56th Drive, 56th Street and Rust Street"
}