{
  "B_Fat": "0",
  "B_Inj": "2",
  "B_KSI": "1",
  "B_Sev": "1",
  "MV_KSI": "1",
  "M_Fat": "0",
  "M_Inj": "10",
  "M_Sev": "1",
  "NodeID_1": "0021430",
  "P_Fat": "1",
  "P_HCC_CLASS": "Top Third",
  "P_HCC_STREETNAME": "West 57th Street",
  "P_Inj": "15",
  "P_KSI": "2",
  "P_Sev": "1",
  "hcc_text": "West 57th Street is a pedestrian high crash corridor (top third for pedestrian deaths and serious injuries per mile in Manhattan)",
  "info": "At West 57th Street and Tenth Avenue, there were 4 deaths and severe injuries in crashes between 2008 and 2012.", 
  "intersection": "West 57th Street and Tenth Avenue"
}